pytest_reportportal/__init__.py
pytest_reportportal/config.py
pytest_reportportal/errors.py
pytest_reportportal/plugin.py
pytest_reportportal/rp_logging.py
pytest_reportportal/service.py
pytest_reportportal-5.5.4.dist-info/licenses/LICENSE
pytest_reportportal-5.5.4.dist-info/METADATA
pytest_reportportal-5.5.4.dist-info/WHEEL
pytest_reportportal-5.5.4.dist-info/entry_points.txt
pytest_reportportal-5.5.4.dist-info/top_level.txt
pytest_reportportal-5.5.4.dist-info/RECORD
