Metadata-Version: 2.4
Name: pytest-reportportal
Version: 5.5.4
Summary: Agent for Reporting results of tests to the Report Portal
Home-page: https://github.com/reportportal/agent-python-pytest
Author: Report Portal Team
Author-email: support@reportportal.io
License: Apache 2.0
Keywords: testing,reporting,reportportal,pytest,agent
Classifier: Framework :: Pytest
Classifier: Programming Language :: Python :: 3.8
Classifier: Programming Language :: Python :: 3.9
Classifier: Programming Language :: Python :: 3.10
Classifier: Programming Language :: Python :: 3.11
Classifier: Programming Language :: Python :: 3.12
Classifier: Programming Language :: Python :: 3.13
License-File: LICENSE
Requires-Dist: dill>=0.3.6
Requires-Dist: pytest>=4.6.10
Requires-Dist: reportportal-client~=5.6.7
Requires-Dist: aenum>=3.1.0
Dynamic: author
Dynamic: author-email
Dynamic: classifier
Dynamic: description
Dynamic: description-content-type
Dynamic: home-page
Dynamic: keywords
Dynamic: license
Dynamic: license-file
Dynamic: requires-dist
Dynamic: summary
